{
  "dataset": "OGBN-MAG",
  "model": "HeteroSAGE",
  "attack": "relation",
  "seed": 2,
  "target_type": "paper",
  "num_classes": 349,
  "target_class": 0,
  "poison_rate": 0.05,
  "trigger_size": 5,
  "sample_mode": "budgeted_induced_subgraph",
  "node_budget_per_type": 50000,
  "raw_graph_stats": {
    "num_node_types": 4,
    "num_edge_types": 7,
    "node_counts": {
      "paper": 736389,
      "author": 1134649,
      "institution": 8740,
      "field_of_study": 59965
    },
    "edge_counts": {
      "('author', 'affiliated_with', 'institution')": 1043998,
      "('author', 'writes', 'paper')": 7145660,
      "('paper', 'cites', 'paper')": 10792672,
      "('paper', 'has_topic', 'field_of_study')": 7505078,
      "('institution', 'rev_affiliated_with', 'author')": 1043998,
      "('paper', 'rev_writes', 'author')": 7145660,
      "('field_of_study', 'rev_has_topic', 'paper')": 7505078
    },
    "total_nodes": 1939743,
    "total_edges": 42182144
  },
  "processed_graph_stats": {
    "num_node_types": 4,
    "num_edge_types": 7,
    "node_counts": {
      "paper": 50000,
      "author": 50000,
      "institution": 8740,
      "field_of_study": 50000
    },
    "edge_counts": {
      "('author', 'affiliated_with', 'institution')": 46205,
      "('author', 'writes', 'paper')": 30857,
      "('paper', 'cites', 'paper')": 71608,
      "('paper', 'has_topic', 'field_of_study')": 419801,
      "('institution', 'rev_affiliated_with', 'author')": 46205,
      "('paper', 'rev_writes', 'author')": 30857,
      "('field_of_study', 'rev_has_topic', 'paper')": 419801
    },
    "total_nodes": 158740,
    "total_edges": 1065334
  },
  "attack_metrics": {
    "clean_acc": 0.31969279050827026,
    "backdoored_clean_acc": 0.28963157534599304,
    "clean_acc_drop": 0.03006121516227722,
    "poisoned_asr": 1.0,
    "poisoned_asr_clean_acc": 0.28900161385536194,
    "natural_target_ratio": 0.0,
    "n_poison_nodes": 833
  },
  "defenses": {
    "hr": {
      "defense_clean_acc": 0.258610337972641,
      "defense_asr": 0.0,
      "defense_asr_clean_acc": 0.2583199441432953,
      "natural_target_ratio": 0.0,
      "defense_name": "HeteroGuard-HR",
      "defense_key": "hr",
      "detection_precision": 1.0,
      "detection_recall": 1.0,
      "detection_f1": 1.0,
      "suspicious_nodes": 833,
      "hard_removed_train_nodes": 833,
      "asr_drop": 1.0,
      "utility_drop": 0.06108245253562927,
      "relative_asr_reduction": 1.0,
      "defense_time_sec": 17.152790784835815,
      "pretrain_time_sec": 6.071059465408325,
      "detection_time_sec": 0.5935046672821045,
      "defense_train_time_sec": 10.23223066329956,
      "eval_time_sec": 0.25438380241394043,
      "peak_gpu_memory_mb": 2480.0,
      "processed_total_nodes": 158740,
      "processed_total_edges": 1065334,
      "processed_num_node_types": 4,
      "processed_num_edge_types": 7,
      "processed_node_counts": {
        "paper": 50000,
        "author": 50000,
        "institution": 8740,
        "field_of_study": 50000
      },
      "processed_edge_counts": {
        "('author', 'affiliated_with', 'institution')": 46205,
        "('author', 'writes', 'paper')": 30857,
        "('paper', 'cites', 'paper')": 71608,
        "('paper', 'has_topic', 'field_of_study')": 419801,
        "('institution', 'rev_affiliated_with', 'author')": 46205,
        "('paper', 'rev_writes', 'author')": 30857,
        "('field_of_study', 'rev_has_topic', 'paper')": 419801
      },
      "pretrain_info": {
        "best_epoch": 29,
        "best_val_acc": 0.1804272085428238
      },
      "train_info": {
        "best_epoch": 49,
        "best_val_acc": 0.24492979049682617,
        "last_loss": 3.1600611209869385,
        "mode": "weighted",
        "hard_removed_train_nodes": 833,
        "use_trigger_unlearning": false
      }
    },
    "unlearn": {
      "defense_clean_acc": 0.2488299459218979,
      "defense_asr": 0.0,
      "defense_asr_clean_acc": 0.24873191118240356,
      "natural_target_ratio": 0.0,
      "defense_name": "HeteroGuard-Unlearn",
      "defense_key": "unlearn",
      "detection_precision": 1.0,
      "detection_recall": 1.0,
      "detection_f1": 1.0,
      "suspicious_nodes": 833,
      "hard_removed_train_nodes": 833,
      "asr_drop": 1.0,
      "utility_drop": 0.07086284458637238,
      "relative_asr_reduction": 1.0,
      "defense_time_sec": 23.664179801940918,
      "pretrain_time_sec": 6.08315372467041,
      "detection_time_sec": 0.604088544845581,
      "defense_train_time_sec": 16.67301297187805,
      "eval_time_sec": 0.3013887405395508,
      "peak_gpu_memory_mb": 2698.0,
      "processed_total_nodes": 158740,
      "processed_total_edges": 1065334,
      "processed_num_node_types": 4,
      "processed_num_edge_types": 7,
      "processed_node_counts": {
        "paper": 50000,
        "author": 50000,
        "institution": 8740,
        "field_of_study": 50000
      },
      "processed_edge_counts": {
        "('author', 'affiliated_with', 'institution')": 46205,
        "('author', 'writes', 'paper')": 30857,
        "('paper', 'cites', 'paper')": 71608,
        "('paper', 'has_topic', 'field_of_study')": 419801,
        "('institution', 'rev_affiliated_with', 'author')": 46205,
        "('paper', 'rev_writes', 'author')": 30857,
        "('field_of_study', 'rev_has_topic', 'paper')": 419801
      },
      "pretrain_info": {
        "best_epoch": 29,
        "best_val_acc": 0.18492738902568817
      },
      "train_info": {
        "best_epoch": 48,
        "best_val_acc": 0.24144965410232544,
        "last_loss": 5.163948059082031,
        "last_clean_loss": 3.4199578762054443,
        "last_unlearn_loss": 1.7438019514083862,
        "last_suppress_loss": 0.0009421078721061349,
        "unlearn_samples": 512,
        "unlearn_lambda": 1.0,
        "target_suppression": 0.2,
        "mode": "weighted_unlearn",
        "hard_removed_train_nodes": 833,
        "use_trigger_unlearning": true
      }
    }
  },
  "runtime": {
    "clean_train_time_sec": 19.86134934425354,
    "attack_generation_time_sec": 0.0296173095703125,
    "poison_train_time_sec": 20.242028951644897,
    "total_runtime_sec": 83.01028084754944,
    "peak_total_gpu_memory_mb": 2698.0
  },
  "clean_train_info": {
    "best_epoch": 97,
    "best_val_acc": 0.3039121627807617,
    "best_train_loss": null,
    "last_loss": 2.2923617362976074,
    "last_val_acc": 0.29173165559768677,
    "save_best": "val_acc"
  },
  "poison_train_info": {
    "best_epoch": 99,
    "best_val_acc": -1.0,
    "best_train_loss": null,
    "last_loss": 2.201220989227295,
    "last_val_acc": 0.28351134061813354,
    "save_best": "last"
  },
  "attacker_info": {
    "attack_name": "relation",
    "target_node_type": "paper",
    "target_class": 0,
    "poison_rate": 0.05,
    "trigger_size": 5,
    "poisoned_node_indices": [
      12177,
      3532,
      5030,
      4511,
      5200,
      621,
      9539,
      14898,
      15171,
      7278,
      15378,
      3646,
      10973,
      12008,
      4699,
      16329,
      3343,
      12778,
      9012,
      6533,
      2042,
      3857,
      12577,
      10660,
      9394,
      5062,
      10483,
      10371,
      13473,
      16056,
      5353,
      4884,
      1275,
      1301,
      9816,
      15544,
      7857,
      15966,
      612,
      3406,
      10297,
      2424,
      2836,
      46059,
      893,
      9551,
      6756,
      8961,
      1345,
      2398,
      14950,
      2013,
      2803,
      15768,
      8236,
      13856,
      15465,
      4512,
      13179,
      914,
      1189,
      10255,
      14534,
      15007,
      10984,
      2060,
      13934,
      11148,
      9409,
      7576,
      4078,
      3080,
      19464,
      11332,
      14556,
      9231,
      9915,
      12006,
      7434,
      6265,
      5473,
      6245,
      13283,
      10675,
      16358,
      6399,
      2901,
      8294,
      9120,
      2643,
      16933,
      15330,
      5235,
      1907,
      16009,
      5035,
      6877,
      15781,
      8769,
      12328,
      14992,
      8735,
      13665,
      106,
      2799,
      3885,
      2066,
      9651,
      9484,
      4172,
      1567,
      3826,
      7050,
      5049,
      5721,
      5835,
      5920,
      3860,
      2559,
      12511,
      7806,
      4736,
      2147,
      15571,
      1202,
      13905,
      15443,
      10099,
      10512,
      15238,
      10176,
      7821,
      10096,
      8799,
      11024,
      5915,
      12289,
      4914,
      10669,
      14489,
      1580,
      4921,
      7880,
      14728,
      3619,
      4329,
      11087,
      1548,
      14232,
      1196,
      11505,
      14234,
      11896,
      6834,
      3754,
      4357,
      9561,
      16144,
      13157,
      10787,
      14067,
      1316,
      8522,
      7750,
      4564,
      8696,
      10315,
      8633,
      7524,
      7563,
      1953,
      4656,
      8421,
      14656,
      5029,
      3167,
      11097,
      817,
      8924,
      9298,
      2519,
      9703,
      6120,
      11957,
      15621,
      1676,
      1207,
      5952,
      11753,
      8450,
      15401,
      4424,
      233,
      6246,
      7663,
      6476,
      255,
      12227,
      46345,
      3596,
      10546,
      3065,
      7435,
      12959,
      7056,
      11640,
      15961,
      555,
      9259,
      11535,
      6049,
      2820,
      2437,
      10162,
      15244,
      13426,
      12286,
      10410,
      1168,
      68,
      4915,
      2717,
      5494,
      8469,
      15120,
      2861,
      16566,
      11934,
      15094,
      9880,
      15926,
      11636,
      8085,
      11414,
      9320,
      7544,
      2038,
      2195,
      552,
      608,
      922,
      3229,
      2110,
      11254,
      7875,
      11844,
      1495,
      9889,
      3282,
      3492,
      906,
      6675,
      7639,
      7301,
      4205,
      19053,
      8240,
      13718,
      1139,
      12016,
      5292,
      215,
      9428,
      8255,
      2535,
      3700,
      1265,
      10739,
      8950,
      18584,
      500,
      308,
      10292,
      6603,
      7022,
      8764,
      974,
      14876,
      1245,
      13749,
      45839,
      10579,
      1409,
      6893,
      12728,
      7122,
      11693,
      16609,
      13382,
      5130,
      17172,
      6702,
      7371,
      2661,
      16731,
      14360,
      16616,
      3877,
      2898,
      9693,
      9972,
      12960,
      13244,
      6819,
      3608,
      7205,
      11502,
      3436,
      7801,
      2326,
      6470,
      9100,
      588,
      3559,
      8918,
      10861,
      2389,
      11216,
      9131,
      15173,
      10150,
      15183,
      5637,
      9797,
      7476,
      15224,
      7783,
      6797,
      2109,
      3048,
      6629,
      17854,
      5628,
      2525,
      2423,
      6808,
      6268,
      13229,
      6296,
      9432,
      12169,
      20190,
      12561,
      2823,
      11361,
      1582,
      2739,
      1694,
      7077,
      6884,
      5210,
      6755,
      14855,
      13050,
      1835,
      16022,
      12226,
      5098,
      11574,
      16026,
      12954,
      8978,
      11572,
      13700,
      5746,
      13417,
      2249,
      5134,
      15749,
      14173,
      5858,
      2624,
      14424,
      11308,
      16528,
      10117,
      10784,
      7192,
      12628,
      5954,
      2862,
      913,
      15762,
      16875,
      15786,
      11250,
      1500,
      8458,
      6353,
      11166,
      1675,
      7939,
      12047,
      11561,
      6123,
      12982,
      3865,
      8196,
      5992,
      11738,
      3576,
      3072,
      5082,
      2786,
      4735,
      10743,
      4576,
      8948,
      8916,
      2382,
      12361,
      11541,
      5406,
      10534,
      11438,
      17453,
      10879,
      1478,
      12606,
      254,
      10087,
      5757,
      9000,
      3757,
      18490,
      12445,
      7298,
      14389,
      6571,
      14540,
      4812,
      773,
      7903,
      2321,
      181,
      7107,
      3705,
      16396,
      14598,
      972,
      4970,
      10441,
      2631,
      1795,
      7102,
      9537,
      9128,
      14401,
      8921,
      15974,
      10842,
      535,
      3021,
      3749,
      14841,
      13594,
      5234,
      11245,
      6671,
      18065,
      11772,
      10089,
      3318,
      578,
      8576,
      1803,
      5456,
      6229,
      6715,
      12706,
      12121,
      12094,
      1966,
      3944,
      20241,
      3059,
      687,
      15195,
      1430,
      10869,
      5367,
      10058,
      7561,
      10034,
      12331,
      3207,
      16814,
      10870,
      8869,
      10280,
      330,
      10486,
      15329,
      9504,
      407,
      12062,
      1157,
      13026,
      11152,
      5909,
      1801,
      4951,
      11939,
      11883,
      5523,
      13752,
      4330,
      14615,
      15665,
      6152,
      3001,
      20945,
      79,
      8652,
      1093,
      14254,
      8149,
      10418,
      3962,
      14177,
      5484,
      2904,
      7459,
      4867,
      12057,
      2522,
      11963,
      325,
      10502,
      14429,
      15438,
      13734,
      10551,
      2938,
      16499,
      10653,
      3910,
      9737,
      9527,
      4685,
      10144,
      15459,
      832,
      12995,
      4543,
      8911,
      8668,
      10077,
      1402,
      14322,
      11070,
      677,
      16940,
      5785,
      12320,
      3303,
      5490,
      10635,
      353,
      13074,
      7829,
      1721,
      7457,
      15374,
      348,
      4754,
      1649,
      4946,
      4825,
      2604,
      26550,
      8708,
      5982,
      12018,
      7723,
      7919,
      4027,
      5119,
      14669,
      2905,
      11277,
      1673,
      7532,
      6431,
      526,
      1374,
      11347,
      5755,
      8206,
      2507,
      3182,
      4815,
      12690,
      5744,
      3957,
      12109,
      5356,
      4102,
      9295,
      12569,
      7922,
      10041,
      16363,
      14334,
      8370,
      9871,
      11650,
      16732,
      12323,
      8148,
      14792,
      6281,
      11055,
      11528,
      1210,
      1285,
      3385,
      8530,
      7924,
      7911,
      9652,
      8298,
      5900,
      347,
      2888,
      2120,
      10445,
      17650,
      16572,
      15699,
      6391,
      3683,
      15535,
      8280,
      4373,
      2674,
      1113,
      16961,
      5894,
      4199,
      1571,
      12242,
      12934,
      4682,
      15962,
      12599,
      16262,
      13297,
      13408,
      2996,
      7416,
      46562,
      8204,
      14328,
      8685,
      15428,
      8589,
      81,
      8660,
      1439,
      2447,
      13639,
      6783,
      2024,
      15317,
      11056,
      6232,
      1610,
      8127,
      13010,
      8821,
      3884,
      13893,
      1067,
      3864,
      3358,
      10553,
      10850,
      18016,
      13392,
      16710,
      4654,
      11449,
      14864,
      6284,
      7395,
      6594,
      14187,
      11394,
      1215,
      1243,
      49049,
      5182,
      2311,
      9122,
      11524,
      7199,
      5293,
      5272,
      19959,
      1459,
      408,
      12817,
      16292,
      4064,
      12832,
      6809,
      2369,
      11157,
      5038,
      13410,
      1004,
      3629,
      1586,
      9463,
      11789,
      16254,
      6775,
      842,
      13193,
      530,
      5578,
      13386,
      4888,
      6014,
      8329,
      10858,
      13044,
      13836,
      7029,
      2554,
      12487,
      13064,
      13928,
      6148,
      8984,
      4067,
      10007,
      4599,
      8989,
      2502,
      5980,
      15036,
      3380,
      18872,
      15326,
      15565,
      5615,
      15518,
      13277,
      12178,
      9898,
      6838,
      14033,
      17542,
      6149,
      2034,
      1436,
      187,
      9084,
      3457,
      1424,
      6580,
      3004,
      12816,
      14974,
      12203,
      11627,
      6079,
      4837,
      1180,
      13668,
      15441,
      8068,
      11966,
      9051,
      18350,
      5759,
      7615,
      5855,
      13811,
      11031,
      326,
      4430,
      12111,
      3055,
      15403,
      4781,
      6446,
      7619,
      5110,
      2421,
      8879,
      837,
      7023,
      5179,
      8506,
      13504,
      7644,
      8005,
      14436,
      9351,
      11218,
      12753,
      15602,
      343,
      4096,
      6134,
      8900,
      4922,
      2529,
      2936,
      8406,
      115,
      5979,
      16158,
      2654,
      8718,
      4165,
      5515,
      10788,
      11740,
      17057,
      10053,
      5341,
      15481,
      10379,
      9272,
      12298,
      1619,
      12059,
      14868,
      14488
    ],
    "trigger_node_indices": {
      "field_of_study": [
        50000,
        50001,
        50002,
        50003,
        50004
      ]
    },
    "trigger_edge_types": [
      "('field_of_study', 'rev_has_topic', 'paper')",
      "('paper', 'has_topic', 'field_of_study')",
      "('field_of_study', 'trigger_link', 'field_of_study')",
      "('field_of_study', 'rev_trigger_link', 'field_of_study')"
    ],
    "target_feature_boost": true,
    "target_feature_strength": 3.0,
    "metadata": {
      "node_types": [
        "paper",
        "author",
        "institution",
        "field_of_study"
      ],
      "edge_types": [
        "('author', 'affiliated_with', 'institution')",
        "('author', 'writes', 'paper')",
        "('paper', 'cites', 'paper')",
        "('paper', 'has_topic', 'field_of_study')",
        "('institution', 'rev_affiliated_with', 'author')",
        "('paper', 'rev_writes', 'author')",
        "('field_of_study', 'rev_has_topic', 'paper')"
      ],
      "target_node_type": "paper",
      "num_classes": 349,
      "trigger_feature_dims": [
        64,
        7,
        49,
        95,
        20
      ],
      "target_feature_boost_dims": [
        50,
        35,
        44,
        121,
        46
      ],
      "poisoned_nodes": 833,
      "trigger_nodes": 5,
      "trigger_type": "relation_hybrid",
      "relation_edge_type": "('field_of_study', 'rev_has_topic', 'paper')",
      "aux_node_type": "field_of_study",
      "use_aux_clique": true,
      "target_feature_boost": true
    }
  },
  "config": {
    "seed": 2,
    "data_dir": "./data",
    "output_dir": "./results_scalability_ogbn_mag_3seeds",
    "save_results": true,
    "device": "cuda",
    "verbose": false,
    "dataset": "OGBN-MAG",
    "model": "HeteroSAGE",
    "attack": "relation",
    "defenses": "hr,unlearn",
    "node_budget_per_type": 50000,
    "hidden_dim": 128,
    "num_heads": 4,
    "num_layers": 2,
    "dropout": 0.5,
    "num_bases": 8,
    "epochs": 100,
    "clean_epochs": null,
    "poison_epochs": null,
    "lr": 0.005,
    "weight_decay": 0.0005,
    "patience": 30,
    "poison_save_best": "last",
    "poison_rate": 0.05,
    "trigger_size": 5,
    "target_class": 0,
    "trigger_strength": 3.0,
    "surrogate_epochs": 20,
    "num_inject": 500,
    "relation_mode": "hybrid",
    "target_feature_strength": 3.0,
    "aux_feature_strength": 4.0,
    "no_aux_clique": false,
    "pretrain_epochs": 30,
    "pretrain_lr": 0.003,
    "defense_epochs": 50,
    "defense_lr": 0.003,
    "defense_weight_decay": 0.0001,
    "detection_ratio": 0.05,
    "use_label_signal": false,
    "min_weight": 0.0,
    "max_downweight": 1.0,
    "unlearn_lambda": 1.0,
    "unlearn_samples": 512,
    "target_suppression": 0.2,
    "include_target_in_unlearning": false
  }
}